inflex_sganfin/__init__.py
inflex_sganfin/main.py
inflex_sganfin/test_table.yaml
inflex_sganfin/data/__init__.py
inflex_sganfin/data/series.py
inflex_sganfin/representations/__init__.py
inflex_sganfin/representations/table.py
inflex_sganfin-0.0.1.dist-info/METADATA
inflex_sganfin-0.0.1.dist-info/WHEEL
inflex_sganfin-0.0.1.dist-info/licenses/LICENSE
inflex_sganfin-0.0.1.dist-info/RECORD
