Metadata-Version: 2.3
Name: inflex_sganfin
Version: 0.0.1
Summary: Flexible report generator
Project-URL: Homepage, https://github.com/sgtyfianalisisfinanciero/inflex-sganfin
Author-email: Álvaro García Tenorio <agarcia@economia.gob.es>
License:                     GNU AFFERO GENERAL PUBLIC LICENSE
License-File: LICENSE
Classifier: Development Status :: 1 - Planning
Classifier: License :: OSI Approved :: GNU Affero General Public License v3 or later (AGPLv3+)
Classifier: Operating System :: OS Independent
Classifier: Programming Language :: Python :: 3.12
Requires-Python: >=3.12
Requires-Dist: python-docx>=1.1.2
Requires-Dist: pyyaml>=6.0.2
